LICENSE
MANIFEST.in
README.md
requirements.txt
setup.py
crdesc/crdesc.py
crdesc.egg-info/PKG-INFO
crdesc.egg-info/SOURCES.txt
crdesc.egg-info/dependency_links.txt
crdesc.egg-info/requires.txt
crdesc.egg-info/top_level.txt