Metadata-Version: 2.1
Name: crdesc
Version: 0.3.2
Summary: crdesc is a python package that produces a textual description from a crmodel.
Home-page: https://github.com/jeremyk6/crdesc/
Author: Jérémy Kalsron
Author-email: jeremy.kalsron@gmail.com  
License: AGPL-3.0
Classifier: License :: OSI Approved :: GNU Affero General Public License v3 or later (AGPLv3+)
Classifier: Programming Language :: Python :: 3
Classifier: Programming Language :: Python :: 3.7
License-File: LICENSE
